LICENSE
MANIFEST.in
README.md
requirements.txt
setup.py
dyndnsimple/__init__.py
dyndnsimple/dyndnsimple.py
dyndnsimple/runner.py
dyndnsimple.egg-info/PKG-INFO
dyndnsimple.egg-info/SOURCES.txt
dyndnsimple.egg-info/dependency_links.txt
dyndnsimple.egg-info/requires.txt
dyndnsimple.egg-info/top_level.txt
scripts/dyndnsimple
test/test_dyndnsimple.py