Metadata-Version: 1.0
Name: dyndnsimple
Version: 0.0.11
Summary: Package for updating DNSimple domain with a WAN IP address.
Home-page: https://github.com/bwghughes/dyndnsimple
Author: Ben Hughes
Author-email: bwghughes@gmail.com
License: UNKNOWN
Platform: UNKNOWN
Classifier: Development Status :: 5 - Production/Stable
Classifier: Intended Audience :: Developers
Classifier: Natural Language :: English
Classifier: License :: OSI Approved :: ISC License (ISCL)
Classifier: Programming Language :: Python
Classifier: Programming Language :: Python :: 2.7
